Compiled from "ArrObject.java"
public class com.aeskilson.bytecode.poc.ArrObject$NestedClass {
  final com.aeskilson.bytecode.poc.ArrObject this$0;

  public com.aeskilson.bytecode.poc.ArrObject$NestedClass(com.aeskilson.bytecode.poc.ArrObject);
    Code:
       0: aload_0
       1: aload_1
       2: putfield      #1                  // Field this$0:Lcom/aeskilson/bytecode/poc/ArrObject;
       5: aload_0
       6: invokespecial #2                  // Method java/lang/Object."<init>":()V
       9: return

  public void apply1();
    Code:
       0: aload_0
       1: getfield      #1                  // Field this$0:Lcom/aeskilson/bytecode/poc/ArrObject;
       4: getfield      #3                  // Field com/aeskilson/bytecode/poc/ArrObject.iVars:[I
       7: iconst_0
       8: iconst_2
       9: iastore
      10: aload_0
      11: getfield      #1                  // Field this$0:Lcom/aeskilson/bytecode/poc/ArrObject;
      14: getfield      #3                  // Field com/aeskilson/bytecode/poc/ArrObject.iVars:[I
      17: iconst_1
      18: iconst_2
      19: iastore
      20: aload_0
      21: getfield      #1                  // Field this$0:Lcom/aeskilson/bytecode/poc/ArrObject;
      24: getfield      #3                  // Field com/aeskilson/bytecode/poc/ArrObject.iVars:[I
      27: iconst_2
      28: iconst_2
      29: iastore
      30: aload_0
      31: getfield      #1                  // Field this$0:Lcom/aeskilson/bytecode/poc/ArrObject;
      34: getfield      #3                  // Field com/aeskilson/bytecode/poc/ArrObject.iVars:[I
      37: iconst_3
      38: iconst_2
      39: iastore
      40: aload_0
      41: getfield      #1                  // Field this$0:Lcom/aeskilson/bytecode/poc/ArrObject;
      44: getfield      #4                  // Field com/aeskilson/bytecode/poc/ArrObject.sVars:[Ljava/lang/String;
      47: iconst_0
      48: ldc           #5                  // String bar
      50: aastore
      51: aload_0
      52: getfield      #1                  // Field this$0:Lcom/aeskilson/bytecode/poc/ArrObject;
      55: getfield      #4                  // Field com/aeskilson/bytecode/poc/ArrObject.sVars:[Ljava/lang/String;
      58: iconst_1
      59: ldc           #5                  // String bar
      61: aastore
      62: aload_0
      63: getfield      #1                  // Field this$0:Lcom/aeskilson/bytecode/poc/ArrObject;
      66: getfield      #4                  // Field com/aeskilson/bytecode/poc/ArrObject.sVars:[Ljava/lang/String;
      69: iconst_2
      70: ldc           #5                  // String bar
      72: aastore
      73: aload_0
      74: getfield      #1                  // Field this$0:Lcom/aeskilson/bytecode/poc/ArrObject;
      77: getfield      #4                  // Field com/aeskilson/bytecode/poc/ArrObject.sVars:[Ljava/lang/String;
      80: iconst_3
      81: ldc           #5                  // String bar
      83: aastore
      84: return

  public void apply2();
    Code:
       0: aload_0
       1: getfield      #1                  // Field this$0:Lcom/aeskilson/bytecode/poc/ArrObject;
       4: getfield      #3                  // Field com/aeskilson/bytecode/poc/ArrObject.iVars:[I
       7: iconst_3
       8: aload_0
       9: getfield      #1                  // Field this$0:Lcom/aeskilson/bytecode/poc/ArrObject;
      12: getfield      #3                  // Field com/aeskilson/bytecode/poc/ArrObject.iVars:[I
      15: iconst_0
      16: iaload
      17: aload_0
      18: getfield      #1                  // Field this$0:Lcom/aeskilson/bytecode/poc/ArrObject;
      21: getfield      #3                  // Field com/aeskilson/bytecode/poc/ArrObject.iVars:[I
      24: iconst_1
      25: iaload
      26: iadd
      27: aload_0
      28: getfield      #1                  // Field this$0:Lcom/aeskilson/bytecode/poc/ArrObject;
      31: getfield      #3                  // Field com/aeskilson/bytecode/poc/ArrObject.iVars:[I
      34: iconst_2
      35: iaload
      36: iadd
      37: aload_0
      38: getfield      #1                  // Field this$0:Lcom/aeskilson/bytecode/poc/ArrObject;
      41: getfield      #3                  // Field com/aeskilson/bytecode/poc/ArrObject.iVars:[I
      44: iconst_3
      45: iaload
      46: iadd
      47: iastore
      48: aload_0
      49: getfield      #1                  // Field this$0:Lcom/aeskilson/bytecode/poc/ArrObject;
      52: getfield      #4                  // Field com/aeskilson/bytecode/poc/ArrObject.sVars:[Ljava/lang/String;
      55: iconst_3
      56: new           #6                  // class java/lang/StringBuilder
      59: dup
      60: invokespecial #7                  // Method java/lang/StringBuilder."<init>":()V
      63: aload_0
      64: getfield      #1                  // Field this$0:Lcom/aeskilson/bytecode/poc/ArrObject;
      67: getfield      #4                  // Field com/aeskilson/bytecode/poc/ArrObject.sVars:[Ljava/lang/String;
      70: iconst_0
      71: aaload
      72: invokevirtual #8                  // Method java/lang/StringBuilder.append:(Ljava/lang/String;)Ljava/lang/StringBuilder;
      75: aload_0
      76: getfield      #1                  // Field this$0:Lcom/aeskilson/bytecode/poc/ArrObject;
      79: getfield      #4                  // Field com/aeskilson/bytecode/poc/ArrObject.sVars:[Ljava/lang/String;
      82: iconst_1
      83: aaload
      84: invokevirtual #8                  // Method java/lang/StringBuilder.append:(Ljava/lang/String;)Ljava/lang/StringBuilder;
      87: aload_0
      88: getfield      #1                  // Field this$0:Lcom/aeskilson/bytecode/poc/ArrObject;
      91: getfield      #4                  // Field com/aeskilson/bytecode/poc/ArrObject.sVars:[Ljava/lang/String;
      94: iconst_2
      95: aaload
      96: invokevirtual #8                  // Method java/lang/StringBuilder.append:(Ljava/lang/String;)Ljava/lang/StringBuilder;
      99: aload_0
     100: getfield      #1                  // Field this$0:Lcom/aeskilson/bytecode/poc/ArrObject;
     103: getfield      #4                  // Field com/aeskilson/bytecode/poc/ArrObject.sVars:[Ljava/lang/String;
     106: iconst_3
     107: aaload
     108: invokevirtual #8                  // Method java/lang/StringBuilder.append:(Ljava/lang/String;)Ljava/lang/StringBuilder;
     111: invokevirtual #9                  // Method java/lang/StringBuilder.toString:()Ljava/lang/String;
     114: aastore
     115: return
}
